pyshipupdate/__init__.py
pyshipupdate/__version__.py
pyshipupdate/aws.py
pyshipupdate/bucket.py
pyshipupdate/exe_return_codes.py
pyshipupdate/os_util.py
pyshipupdate/py.typed
pyshipupdate/updater.py
pyshipupdate/version.py
pyshipupdate-0.1.0.dist-info/LICENSE
pyshipupdate-0.1.0.dist-info/METADATA
pyshipupdate-0.1.0.dist-info/WHEEL
pyshipupdate-0.1.0.dist-info/top_level.txt
pyshipupdate-0.1.0.dist-info/RECORD
