Metadata-Version: 2.1
Name: pyshipupdate
Version: 0.1.0
Summary: self-update applications frozen/installed by pyship
Home-page: https://github.com/jamesabel/pyshipupdate
Author: abel
Author-email: j@abel.co
License: MIT License
Download-URL: https://github.com/jamesabel/pyshipupdate
Keywords: freezer,installer,ship
Platform: UNKNOWN
License-File: LICENSE
Requires-Dist: balsa
Requires-Dist: requests
Requires-Dist: attrs
Requires-Dist: typeguard
Requires-Dist: semver
Requires-Dist: python-dateutil
Requires-Dist: boto3
Requires-Dist: awsimple
